spring_aws/__init__.py
spring_aws/aws_python.py
spring_aws/aws_utils.py
spring_aws/core.py
spring_aws/create_loadbalancer.py
spring_aws/helpers.py
spring_aws/instance_schedule.py
spring_aws/instance_state.py
spring_aws/lambda-alerting.py
spring_aws/lb_add_remove.py
spring_aws/modify_lb_membership.py
spring_aws/scratch_space.py
spring_aws/toggle_alerts.py
spring_aws/utils.py
spring_aws-1.0.0.dist-info/DESCRIPTION.rst
spring_aws-1.0.0.dist-info/METADATA
spring_aws-1.0.0.dist-info/RECORD
spring_aws-1.0.0.dist-info/WHEEL
spring_aws-1.0.0.dist-info/metadata.json
spring_aws-1.0.0.dist-info/top_level.txt
