Metadata-Version: 2.0
Name: spring-aws
Version: 1.0.0
Summary: Generic AWS Utilities
Home-page: UNKNOWN
Author: Jiwan Rai
Author-email: jiwan@sheriemuijs.com
License: MIT License
